{"url": "https://api.github.com/repos/rails-girls-summer-of-code/rgsoc-teams/issues/256", "repository_url": "https://api.github.com/repos/rails-girls-summer-of-code/rgsoc-teams", "labels_url": "https://api.github.com/repos/rails-girls-summer-of-code/rgsoc-teams/issues/256/labels{/name}", "comments_url": "https://api.github.com/repos/rails-girls-summer-of-code/rgsoc-teams/issues/256/comments", "events_url": "https://api.github.com/repos/rails-girls-summer-of-code/rgsoc-teams/issues/256/events", "html_url": "https://github.com/rails-girls-summer-of-code/rgsoc-teams/issues/256", "id": 94029480, "number": 256, "title": "Automatic reminder for daily log", "user": {"login": "anikalindtner", "id": 1711357, "avatar_url": "https://avatars1.githubusercontent.com/u/1711357?v=4", "gravatar_id": "", "url": "https://api.github.com/users/anikalindtner", "html_url": "https://github.com/anikalindtner", "followers_url": "https://api.github.com/users/anikalindtner/followers", "following_url": "https://api.github.com/users/anikalindtner/following{/other_user}", "gists_url": "https://api.github.com/users/anikalindtner/gists{/gist_id}", "starred_url": "https://api.github.com/users/anikalindtner/starred{/owner}{/repo}", "subscriptions_url": "https://api.github.com/users/anikalindtner/subscriptions", "organizations_url": "https://api.github.com/users/anikalindtner/orgs", "repos_url": "https://api.github.com/users/anikalindtner/repos", "events_url": "https://api.github.com/users/anikalindtner/events{/privacy}", "received_events_url": "https://api.github.com/users/anikalindtner/received_events", "type": "User", "site_admin": false}, "labels": [{"id": 318444345, "url": "https://api.github.com/repos/rails-girls-summer-of-code/rgsoc-teams/labels/rgsoc-2016", "name": "rgsoc-2016", "color": "0052cc", "default": false}], "state": "closed", "locked": false, "assignee": {"login": "michaelem", "id": 182228, "avatar_url": "https://avatars3.githubusercontent.com/u/182228?v=4", "gravatar_id": "", "url": "https://api.github.com/users/michaelem", "html_url": "https://github.com/michaelem", "followers_url": "https://api.github.com/users/michaelem/followers", "following_url": "https://api.github.com/users/michaelem/following{/other_user}", "gists_url": "https://api.github.com/users/michaelem/gists{/gist_id}", "starred_url": "https://api.github.com/users/michaelem/starred{/owner}{/repo}", "subscriptions_url": "https://api.github.com/users/michaelem/subscriptions", "organizations_url": "https://api.github.com/users/michaelem/orgs", "repos_url": "https://api.github.com/users/michaelem/repos", "events_url": "https://api.github.com/users/michaelem/events{/privacy}", "received_events_url": "https://api.github.com/users/michaelem/received_events", "type": "User", "site_admin": false}, "assignees": [{"login": "michaelem", "id": 182228, "avatar_url": "https://avatars3.githubusercontent.com/u/182228?v=4", "gravatar_id": "", "url": "https://api.github.com/users/michaelem", "html_url": "https://github.com/michaelem", "followers_url": "https://api.github.com/users/michaelem/followers", "following_url": "https://api.github.com/users/michaelem/following{/other_user}", "gists_url": "https://api.github.com/users/michaelem/gists{/gist_id}", "starred_url": "https://api.github.com/users/michaelem/starred{/owner}{/repo}", "subscriptions_url": "https://api.github.com/users/michaelem/subscriptions", "organizations_url": "https://api.github.com/users/michaelem/orgs", "repos_url": "https://api.github.com/users/michaelem/repos", "events_url": "https://api.github.com/users/michaelem/events{/privacy}", "received_events_url": "https://api.github.com/users/michaelem/received_events", "type": "User", "site_admin": false}, {"login": "anikalindtner", "id": 1711357, "avatar_url": "https://avatars1.githubusercontent.com/u/1711357?v=4", "gravatar_id": "", "url": "https://api.github.com/users/anikalindtner", "html_url": "https://github.com/anikalindtner", "followers_url": "https://api.github.com/users/anikalindtner/followers", "following_url": "https://api.github.com/users/anikalindtner/following{/other_user}", "gists_url": "https://api.github.com/users/anikalindtner/gists{/gist_id}", "starred_url": "https://api.github.com/users/anikalindtner/starred{/owner}{/repo}", "subscriptions_url": "https://api.github.com/users/anikalindtner/subscriptions", "organizations_url": "https://api.github.com/users/anikalindtner/orgs", "repos_url": "https://api.github.com/users/anikalindtner/repos", "events_url": "https://api.github.com/users/anikalindtner/events{/privacy}", "received_events_url": "https://api.github.com/users/anikalindtner/received_events", "type": "User", "site_admin": false}], "milestone": null, "comments": 17, "created_at": "2015-07-09T12:04:04Z", "updated_at": "2016-07-13T13:19:46Z", "closed_at": "2016-07-13T13:19:41Z", "author_association": "OWNER", "body_html": "<p>As we talked about in our weekly organizer hangout yesterday, a lot of what the supervisors are doing is nagging teams to get stuff done. Which wears them down and shouldn't be the main task of our supervisors. So I thought about how to make at least <em>some</em> of the process automated to take it out of their hands. And one thing would be to send an email reminder at hour xy to the team if they haven't filled out their daily log. This way we nag them without having to do it ourselves and they get accustomed to doing it everyday from the beginning on.</p>\n<p>Exception would have to be weekends.</p>\n<p><a href=\"https://github.com/sareg0\" class=\"user-mention\">@sareg0</a> was interested in helping to think about how we could implement something like that.</p>\n<p>Comments? Opinions?</p>", "body_text": "As we talked about in our weekly organizer hangout yesterday, a lot of what the supervisors are doing is nagging teams to get stuff done. Which wears them down and shouldn't be the main task of our supervisors. So I thought about how to make at least some of the process automated to take it out of their hands. And one thing would be to send an email reminder at hour xy to the team if they haven't filled out their daily log. This way we nag them without having to do it ourselves and they get accustomed to doing it everyday from the beginning on.\nException would have to be weekends.\n@sareg0 was interested in helping to think about how we could implement something like that.\nComments? Opinions?", "body": "As we talked about in our weekly organizer hangout yesterday, a lot of what the supervisors are doing is nagging teams to get stuff done. Which wears them down and shouldn't be the main task of our supervisors. So I thought about how to make at least _some_ of the process automated to take it out of their hands. And one thing would be to send an email reminder at hour xy to the team if they haven't filled out their daily log. This way we nag them without having to do it ourselves and they get accustomed to doing it everyday from the beginning on. \n\nException would have to be weekends. \n\n@sareg0 was interested in helping to think about how we could implement something like that. \n\nComments? Opinions? \n"}