{"url": "https://api.github.com/repos/rails-girls-summer-of-code/rgsoc-teams/issues/comments/354615959", "html_url": "https://github.com/rails-girls-summer-of-code/rgsoc-teams/pull/900#issuecomment-354615959", "issue_url": "https://api.github.com/repos/rails-girls-summer-of-code/rgsoc-teams/issues/900", "id": 354615959, "user": {"login": "F3PiX", "id": 6314687, "avatar_url": "https://avatars1.githubusercontent.com/u/6314687?v=4", "gravatar_id": "", "url": "https://api.github.com/users/F3PiX", "html_url": "https://github.com/F3PiX", "followers_url": "https://api.github.com/users/F3PiX/followers", "following_url": "https://api.github.com/users/F3PiX/following{/other_user}", "gists_url": "https://api.github.com/users/F3PiX/gists{/gist_id}", "starred_url": "https://api.github.com/users/F3PiX/starred{/owner}{/repo}", "subscriptions_url": "https://api.github.com/users/F3PiX/subscriptions", "organizations_url": "https://api.github.com/users/F3PiX/orgs", "repos_url": "https://api.github.com/users/F3PiX/repos", "events_url": "https://api.github.com/users/F3PiX/events{/privacy}", "received_events_url": "https://api.github.com/users/F3PiX/received_events", "type": "User", "site_admin": false}, "created_at": "2017-12-31T17:36:49Z", "updated_at": "2017-12-31T17:36:49Z", "author_association": "MEMBER", "body_html": "<p>I totally agree with all your conclusions, thanks for the explanations.<br>\n<g-emoji class=\"g-emoji\" alias=\"fireworks\" fallback-src=\"https://assets-cdn.github.com/images/icons/emoji/unicode/1f386.png\">\ud83c\udf86</g-emoji></p>", "body_text": "I totally agree with all your conclusions, thanks for the explanations.\n\ud83c\udf86", "body": "I totally agree with all your conclusions, thanks for the explanations. \r\n\ud83c\udf86 \r\n"}