{"url": "https://api.github.com/repos/rails-girls-summer-of-code/rgsoc-teams/pulls/comments/162054589", "pull_request_review_id": 89444985, "id": 162054589, "diff_hunk": "@@ -25,11 +25,12 @@ def edit\n   end\n \n   def index\n-    if Season.current.active?\n-      @projects = Project.selected\n-    else\n-      @projects = Project.in_current_season.where(aasm_state: %w(accepted proposed))\n-    end\n+    season = Season.find_by(name: params['filter']) || Season.current\n+    @projects = if season.current? and !season.active?", "path": "app/controllers/projects_controller.rb", "position": 10, "original_position": 10, "commit_id": "bc2fe44cb300ce4481c00a998ecb38c4614294f6", "original_commit_id": "bc2fe44cb300ce4481c00a998ecb38c4614294f6", "user": {"login": "carpodaster", "id": 164400, "avatar_url": "https://avatars2.githubusercontent.com/u/164400?v=4", "gravatar_id": "", "url": "https://api.github.com/users/carpodaster", "html_url": "https://github.com/carpodaster", "followers_url": "https://api.github.com/users/carpodaster/followers", "following_url": "https://api.github.com/users/carpodaster/following{/other_user}", "gists_url": "https://api.github.com/users/carpodaster/gists{/gist_id}", "starred_url": "https://api.github.com/users/carpodaster/starred{/owner}{/repo}", "subscriptions_url": "https://api.github.com/users/carpodaster/subscriptions", "organizations_url": "https://api.github.com/users/carpodaster/orgs", "repos_url": "https://api.github.com/users/carpodaster/repos", "events_url": "https://api.github.com/users/carpodaster/events{/privacy}", "received_events_url": "https://api.github.com/users/carpodaster/received_events", "type": "User", "site_admin": false}, "body": "`and`/`or`  for control flow! Currently tattooing this onto my knees! \ud83d\ude04   Thanks!", "created_at": "2018-01-17T13:49:59Z", "updated_at": "2018-01-17T14:42:15Z", "html_url": "https://github.com/rails-girls-summer-of-code/rgsoc-teams/pull/910#discussion_r162054589", "pull_request_url": "https://api.github.com/repos/rails-girls-summer-of-code/rgsoc-teams/pulls/910", "author_association": "OWNER", "_links": {"self": {"href": "https://api.github.com/repos/rails-girls-summer-of-code/rgsoc-teams/pulls/comments/162054589"}, "html": {"href": "https://github.com/rails-girls-summer-of-code/rgsoc-teams/pull/910#discussion_r162054589"}, "pull_request": {"href": "https://api.github.com/repos/rails-girls-summer-of-code/rgsoc-teams/pulls/910"}}, "body_html": "<p><code>and</code>/<code>or</code>  for control flow! Currently tattooing this onto my knees! <g-emoji class=\"g-emoji\" alias=\"smile\" fallback-src=\"https://assets-cdn.github.com/images/icons/emoji/unicode/1f604.png\">\ud83d\ude04</g-emoji>   Thanks!</p>", "body_text": "and/or  for control flow! Currently tattooing this onto my knees! \ud83d\ude04   Thanks!", "in_reply_to_id": 162046907}