{"url": "https://api.github.com/repos/rails-girls-summer-of-code/rgsoc-teams/issues/614", "repository_url": "https://api.github.com/repos/rails-girls-summer-of-code/rgsoc-teams", "labels_url": "https://api.github.com/repos/rails-girls-summer-of-code/rgsoc-teams/issues/614/labels{/name}", "comments_url": "https://api.github.com/repos/rails-girls-summer-of-code/rgsoc-teams/issues/614/comments", "events_url": "https://api.github.com/repos/rails-girls-summer-of-code/rgsoc-teams/issues/614/events", "html_url": "https://github.com/rails-girls-summer-of-code/rgsoc-teams/issues/614", "id": 201015687, "number": 614, "title": "Improvements to the help page", "user": {"login": "alicetragedy", "id": 3143348, "avatar_url": "https://avatars1.githubusercontent.com/u/3143348?v=4", "gravatar_id": "", "url": "https://api.github.com/users/alicetragedy", "html_url": "https://github.com/alicetragedy", "followers_url": "https://api.github.com/users/alicetragedy/followers", "following_url": "https://api.github.com/users/alicetragedy/following{/other_user}", "gists_url": "https://api.github.com/users/alicetragedy/gists{/gist_id}", "starred_url": "https://api.github.com/users/alicetragedy/starred{/owner}{/repo}", "subscriptions_url": "https://api.github.com/users/alicetragedy/subscriptions", "organizations_url": "https://api.github.com/users/alicetragedy/orgs", "repos_url": "https://api.github.com/users/alicetragedy/repos", "events_url": "https://api.github.com/users/alicetragedy/events{/privacy}", "received_events_url": "https://api.github.com/users/alicetragedy/received_events", "type": "User", "site_admin": false}, "labels": [{"id": 183380268, "url": "https://api.github.com/repos/rails-girls-summer-of-code/rgsoc-teams/labels/styling", "name": "styling", "color": "d4c5f9", "default": false}], "state": "closed", "locked": false, "assignee": {"login": "alicetragedy", "id": 3143348, "avatar_url": "https://avatars1.githubusercontent.com/u/3143348?v=4", "gravatar_id": "", "url": "https://api.github.com/users/alicetragedy", "html_url": "https://github.com/alicetragedy", "followers_url": "https://api.github.com/users/alicetragedy/followers", "following_url": "https://api.github.com/users/alicetragedy/following{/other_user}", "gists_url": "https://api.github.com/users/alicetragedy/gists{/gist_id}", "starred_url": "https://api.github.com/users/alicetragedy/starred{/owner}{/repo}", "subscriptions_url": "https://api.github.com/users/alicetragedy/subscriptions", "organizations_url": "https://api.github.com/users/alicetragedy/orgs", "repos_url": "https://api.github.com/users/alicetragedy/repos", "events_url": "https://api.github.com/users/alicetragedy/events{/privacy}", "received_events_url": "https://api.github.com/users/alicetragedy/received_events", "type": "User", "site_admin": false}, "assignees": [{"login": "alicetragedy", "id": 3143348, "avatar_url": "https://avatars1.githubusercontent.com/u/3143348?v=4", "gravatar_id": "", "url": "https://api.github.com/users/alicetragedy", "html_url": "https://github.com/alicetragedy", "followers_url": "https://api.github.com/users/alicetragedy/followers", "following_url": "https://api.github.com/users/alicetragedy/following{/other_user}", "gists_url": "https://api.github.com/users/alicetragedy/gists{/gist_id}", "starred_url": "https://api.github.com/users/alicetragedy/starred{/owner}{/repo}", "subscriptions_url": "https://api.github.com/users/alicetragedy/subscriptions", "organizations_url": "https://api.github.com/users/alicetragedy/orgs", "repos_url": "https://api.github.com/users/alicetragedy/repos", "events_url": "https://api.github.com/users/alicetragedy/events{/privacy}", "received_events_url": "https://api.github.com/users/alicetragedy/received_events", "type": "User", "site_admin": false}], "milestone": {"url": "https://api.github.com/repos/rails-girls-summer-of-code/rgsoc-teams/milestones/7", "html_url": "https://github.com/rails-girls-summer-of-code/rgsoc-teams/milestone/7", "labels_url": "https://api.github.com/repos/rails-girls-summer-of-code/rgsoc-teams/milestones/7/labels", "id": 1648818, "number": 7, "title": "Application Process 2017", "description": " https://github.com/rails-girls-summer-of-code/organization/issues/103 ", "creator": {"login": "carpodaster", "id": 164400, "avatar_url": "https://avatars2.githubusercontent.com/u/164400?v=4", "gravatar_id": "", "url": "https://api.github.com/users/carpodaster", "html_url": "https://github.com/carpodaster", "followers_url": "https://api.github.com/users/carpodaster/followers", "following_url": "https://api.github.com/users/carpodaster/following{/other_user}", "gists_url": "https://api.github.com/users/carpodaster/gists{/gist_id}", "starred_url": "https://api.github.com/users/carpodaster/starred{/owner}{/repo}", "subscriptions_url": "https://api.github.com/users/carpodaster/subscriptions", "organizations_url": "https://api.github.com/users/carpodaster/orgs", "repos_url": "https://api.github.com/users/carpodaster/repos", "events_url": "https://api.github.com/users/carpodaster/events{/privacy}", "received_events_url": "https://api.github.com/users/carpodaster/received_events", "type": "User", "site_admin": false}, "open_issues": 5, "closed_issues": 16, "state": "open", "created_at": "2016-03-16T19:28:41Z", "updated_at": "2017-09-05T10:41:44Z", "due_on": "2017-01-31T08:00:00Z", "closed_at": null}, "comments": 4, "created_at": "2017-01-16T13:11:26Z", "updated_at": "2017-03-07T09:51:44Z", "closed_at": "2017-03-07T09:51:40Z", "author_association": "OWNER", "body_html": "<p>The help page(s) for students were a bit confusing last year, so we should definitely review and improve them (especially if some things have changed in the application process) before the open the applications. This includes:</p>\n<ul class=\"contains-task-list\">\n<li class=\"task-list-item\"><input checked=\"\" class=\"task-list-item-checkbox\" disabled=\"\" id=\"\" type=\"checkbox\"> review \u201cHow to create an account\u201d and \u201chow to fill out your application\u201d pages</li>\n<li class=\"task-list-item\"><input checked=\"\" class=\"task-list-item-checkbox\" disabled=\"\" id=\"\" type=\"checkbox\"> review text on the main help page</li>\n<li class=\"task-list-item\"><input checked=\"\" class=\"task-list-item-checkbox\" disabled=\"\" id=\"\" type=\"checkbox\"> make a link to the help page more prominent?</li>\n<li class=\"task-list-item\"><input checked=\"\" class=\"task-list-item-checkbox\" disabled=\"\" id=\"\" type=\"checkbox\"> improve headings and structure of the help page</li>\n<li class=\"task-list-item\"><input checked=\"\" class=\"task-list-item-checkbox\" disabled=\"\" id=\"\" type=\"checkbox\"> improve \u201chow to confirm your coach status\u201d (add screenshot for coaches to confirm themselves, improve wording)</li>\n<li class=\"task-list-item\"><input checked=\"\" class=\"task-list-item-checkbox\" disabled=\"\" id=\"\" type=\"checkbox\"> add page \u201chow to contact your mentor\u201d (could also be part of \u201chow to fill your application\u201d) \u2014 with screenshot of where to find user information</li>\n<li class=\"task-list-item\"><input checked=\"\" class=\"task-list-item-checkbox\" disabled=\"\" id=\"\" type=\"checkbox\"> add instructions about how to add coaching company info to application form (i.e. needs to be added to the \u201cAnything else to add?\u201d field, cannot be named, can also be added to coach profiles and named there if necessary)</li>\n</ul>", "body_text": "The help page(s) for students were a bit confusing last year, so we should definitely review and improve them (especially if some things have changed in the application process) before the open the applications. This includes:\n\n review \u201cHow to create an account\u201d and \u201chow to fill out your application\u201d pages\n review text on the main help page\n make a link to the help page more prominent?\n improve headings and structure of the help page\n improve \u201chow to confirm your coach status\u201d (add screenshot for coaches to confirm themselves, improve wording)\n add page \u201chow to contact your mentor\u201d (could also be part of \u201chow to fill your application\u201d) \u2014 with screenshot of where to find user information\n add instructions about how to add coaching company info to application form (i.e. needs to be added to the \u201cAnything else to add?\u201d field, cannot be named, can also be added to coach profiles and named there if necessary)", "body": "The help page(s) for students were a bit confusing last year, so we should definitely review and improve them (especially if some things have changed in the application process) before the open the applications. This includes:\r\n- [x] review \u201cHow to create an account\u201d and \u201chow to fill out your application\u201d pages\r\n- [x] review text on the main help page\r\n- [x] make a link to the help page more prominent?\r\n- [x] improve headings and structure of the help page \r\n- [x] improve \u201chow to confirm your coach status\u201d (add screenshot for coaches to confirm themselves, improve wording)\r\n- [x] add page \u201chow to contact your mentor\u201d (could also be part of \u201chow to fill your application\u201d) \u2014 with screenshot of where to find user information\r\n- [x] add instructions about how to add coaching company info to application form (i.e. needs to be added to the \u201cAnything else to add?\u201d field, cannot be named, can also be added to coach profiles and named there if necessary)"}