{"url": "https://api.github.com/repos/rails-girls-summer-of-code/rgsoc-teams/pulls/comments/119991271", "pull_request_review_id": 41924675, "id": 119991271, "diff_hunk": "@@ -12,12 +12,16 @@ class Conference < ActiveRecord::Base\n   scope :ordered, ->(sort = {}) { order([sort[:order] || 'starts_on, name', sort[:direction] || 'asc'].join(' ')) }\n   scope :in_current_season, -> { where(season: Season.current) }\n \n+  def dates\n+    DateRange.new(start_date: starts_on, end_date: ends_on)\n+  end\n+  \n   def chronological_dates\n     unless starts_on <= ends_on\n       errors.add(:ends_on, 'must be a later date than start date')\n     end\n   end\n-\n+  ", "path": "app/models/conference.rb", "position": 14, "original_position": 14, "commit_id": "4a2df11759069bd2507464bfbda8515466cdc3eb", "original_commit_id": "eadd69f85d996fe8d8a0e3de538862e958e6eeaa", "user": {"login": "F3PiX", "id": 6314687, "avatar_url": "https://avatars1.githubusercontent.com/u/6314687?v=4", "gravatar_id": "", "url": "https://api.github.com/users/F3PiX", "html_url": "https://github.com/F3PiX", "followers_url": "https://api.github.com/users/F3PiX/followers", "following_url": "https://api.github.com/users/F3PiX/following{/other_user}", "gists_url": "https://api.github.com/users/F3PiX/gists{/gist_id}", "starred_url": "https://api.github.com/users/F3PiX/starred{/owner}{/repo}", "subscriptions_url": "https://api.github.com/users/F3PiX/subscriptions", "organizations_url": "https://api.github.com/users/F3PiX/orgs", "repos_url": "https://api.github.com/users/F3PiX/repos", "events_url": "https://api.github.com/users/F3PiX/events{/privacy}", "received_events_url": "https://api.github.com/users/F3PiX/received_events", "type": "User", "site_admin": false}, "body": "I removed them, not sure why it still shows up here. ", "created_at": "2017-06-03T17:57:39Z", "updated_at": "2017-06-04T12:40:34Z", "html_url": "https://github.com/rails-girls-summer-of-code/rgsoc-teams/pull/748#discussion_r119991271", "pull_request_url": "https://api.github.com/repos/rails-girls-summer-of-code/rgsoc-teams/pulls/748", "author_association": "MEMBER", "_links": {"self": {"href": "https://api.github.com/repos/rails-girls-summer-of-code/rgsoc-teams/pulls/comments/119991271"}, "html": {"href": "https://github.com/rails-girls-summer-of-code/rgsoc-teams/pull/748#discussion_r119991271"}, "pull_request": {"href": "https://api.github.com/repos/rails-girls-summer-of-code/rgsoc-teams/pulls/748"}}, "body_html": "<p>I removed them, not sure why it still shows up here.</p>", "body_text": "I removed them, not sure why it still shows up here.", "in_reply_to_id": 119590163}