{"url": "https://api.github.com/repos/rails-girls-summer-of-code/rgsoc-teams/pulls/comments/119711449", "pull_request_review_id": 41617603, "id": 119711449, "diff_hunk": "@@ -41,6 +41,16 @@\n       end\n     end\n   end\n+  \n+  describe '#dates' do\n+    subject { FactoryGirl.build_stubbed(:conference) }\n+    \n+    it 'has a date range' do", "path": "spec/models/conference_spec.rb", "position": null, "original_position": 8, "commit_id": "4a2df11759069bd2507464bfbda8515466cdc3eb", "original_commit_id": "eadd69f85d996fe8d8a0e3de538862e958e6eeaa", "user": {"login": "carpodaster", "id": 164400, "avatar_url": "https://avatars2.githubusercontent.com/u/164400?v=4", "gravatar_id": "", "url": "https://api.github.com/users/carpodaster", "html_url": "https://github.com/carpodaster", "followers_url": "https://api.github.com/users/carpodaster/followers", "following_url": "https://api.github.com/users/carpodaster/following{/other_user}", "gists_url": "https://api.github.com/users/carpodaster/gists{/gist_id}", "starred_url": "https://api.github.com/users/carpodaster/starred{/owner}{/repo}", "subscriptions_url": "https://api.github.com/users/carpodaster/subscriptions", "organizations_url": "https://api.github.com/users/carpodaster/orgs", "repos_url": "https://api.github.com/users/carpodaster/repos", "events_url": "https://api.github.com/users/carpodaster/events{/privacy}", "received_events_url": "https://api.github.com/users/carpodaster/received_events", "type": "User", "site_admin": false}, "body": "(The Pipeline Operator Influence   `|>` is strong in this one :wink: :heart_decoration:)", "created_at": "2017-06-01T19:47:07Z", "updated_at": "2017-06-04T12:40:34Z", "html_url": "https://github.com/rails-girls-summer-of-code/rgsoc-teams/pull/748#discussion_r119711449", "pull_request_url": "https://api.github.com/repos/rails-girls-summer-of-code/rgsoc-teams/pulls/748", "author_association": "OWNER", "_links": {"self": {"href": "https://api.github.com/repos/rails-girls-summer-of-code/rgsoc-teams/pulls/comments/119711449"}, "html": {"href": "https://github.com/rails-girls-summer-of-code/rgsoc-teams/pull/748#discussion_r119711449"}, "pull_request": {"href": "https://api.github.com/repos/rails-girls-summer-of-code/rgsoc-teams/pulls/748"}}, "body_html": "<p>(The Pipeline Operator Influence   <code>|&gt;</code> is strong in this one <g-emoji class=\"g-emoji\" alias=\"wink\" fallback-src=\"https://assets-cdn.github.com/images/icons/emoji/unicode/1f609.png\">\ud83d\ude09</g-emoji> <g-emoji class=\"g-emoji\" alias=\"heart_decoration\" fallback-src=\"https://assets-cdn.github.com/images/icons/emoji/unicode/1f49f.png\">\ud83d\udc9f</g-emoji>)</p>", "body_text": "(The Pipeline Operator Influence   |> is strong in this one \ud83d\ude09 \ud83d\udc9f)", "in_reply_to_id": 119589687}