{"url": "https://api.github.com/repos/rails-girls-summer-of-code/rgsoc-teams/pulls/comments/134696767", "pull_request_review_id": 58016590, "id": 134696767, "diff_hunk": "@@ -33,10 +33,7 @@ def redirect\n   private\n \n   def build_conference\n-    conference = Conference.new(conference_params)\n-    conference.season_id = current_season.id\n-    conference.gid = generate_gid\n-    conference\n+    Conference.new(conference_params.merge(season: current_season, gid: generate_gid))", "path": "app/controllers/conferences_controller.rb", "position": null, "original_position": 8, "commit_id": "0dbe14897fe1e7d2c41fc95298707c9a34fa6b48", "original_commit_id": "95b3a953d095e8c2c6817f27a2647b970fc9d7e3", "user": {"login": "F3PiX", "id": 6314687, "avatar_url": "https://avatars1.githubusercontent.com/u/6314687?v=4", "gravatar_id": "", "url": "https://api.github.com/users/F3PiX", "html_url": "https://github.com/F3PiX", "followers_url": "https://api.github.com/users/F3PiX/followers", "following_url": "https://api.github.com/users/F3PiX/following{/other_user}", "gists_url": "https://api.github.com/users/F3PiX/gists{/gist_id}", "starred_url": "https://api.github.com/users/F3PiX/starred{/owner}{/repo}", "subscriptions_url": "https://api.github.com/users/F3PiX/subscriptions", "organizations_url": "https://api.github.com/users/F3PiX/orgs", "repos_url": "https://api.github.com/users/F3PiX/repos", "events_url": "https://api.github.com/users/F3PiX/events{/privacy}", "received_events_url": "https://api.github.com/users/F3PiX/received_events", "type": "User", "site_admin": false}, "body": "\ud83d\udc4d Nice!", "created_at": "2017-08-23T09:08:54Z", "updated_at": "2017-09-13T16:42:22Z", "html_url": "https://github.com/rails-girls-summer-of-code/rgsoc-teams/pull/828#discussion_r134696767", "pull_request_url": "https://api.github.com/repos/rails-girls-summer-of-code/rgsoc-teams/pulls/828", "author_association": "MEMBER", "_links": {"self": {"href": "https://api.github.com/repos/rails-girls-summer-of-code/rgsoc-teams/pulls/comments/134696767"}, "html": {"href": "https://github.com/rails-girls-summer-of-code/rgsoc-teams/pull/828#discussion_r134696767"}, "pull_request": {"href": "https://api.github.com/repos/rails-girls-summer-of-code/rgsoc-teams/pulls/828"}}, "body_html": "<p><g-emoji class=\"g-emoji\" alias=\"+1\" fallback-src=\"https://assets-cdn.github.com/images/icons/emoji/unicode/1f44d.png\">\ud83d\udc4d</g-emoji> Nice!</p>", "body_text": "\ud83d\udc4d Nice!"}