{"url": "https://api.github.com/repos/rails-girls-summer-of-code/rgsoc-teams/issues/903", "repository_url": "https://api.github.com/repos/rails-girls-summer-of-code/rgsoc-teams", "labels_url": "https://api.github.com/repos/rails-girls-summer-of-code/rgsoc-teams/issues/903/labels{/name}", "comments_url": "https://api.github.com/repos/rails-girls-summer-of-code/rgsoc-teams/issues/903/comments", "events_url": "https://api.github.com/repos/rails-girls-summer-of-code/rgsoc-teams/issues/903/events", "html_url": "https://github.com/rails-girls-summer-of-code/rgsoc-teams/issues/903", "id": 285653094, "number": 903, "title": "Investigate possible AWS errors", "user": {"login": "carpodaster", "id": 164400, "avatar_url": "https://avatars2.githubusercontent.com/u/164400?v=4", "gravatar_id": "", "url": "https://api.github.com/users/carpodaster", "html_url": "https://github.com/carpodaster", "followers_url": "https://api.github.com/users/carpodaster/followers", "following_url": "https://api.github.com/users/carpodaster/following{/other_user}", "gists_url": "https://api.github.com/users/carpodaster/gists{/gist_id}", "starred_url": "https://api.github.com/users/carpodaster/starred{/owner}{/repo}", "subscriptions_url": "https://api.github.com/users/carpodaster/subscriptions", "organizations_url": "https://api.github.com/users/carpodaster/orgs", "repos_url": "https://api.github.com/users/carpodaster/repos", "events_url": "https://api.github.com/users/carpodaster/events{/privacy}", "received_events_url": "https://api.github.com/users/carpodaster/received_events", "type": "User", "site_admin": false}, "labels": [], "state": "open", "locked": false, "assignee": null, "assignees": [], "milestone": null, "comments": 0, "created_at": "2018-01-03T10:51:35Z", "updated_at": "2018-01-03T10:51:35Z", "closed_at": null, "author_association": "OWNER", "body_html": "<p>Follow-up to <a href=\"https://github.com/rails-girls-summer-of-code/rgsoc-teams/issues/853\" class=\"issue-link js-issue-link\" data-error-text=\"Failed to load issue title\" data-id=\"257106672\" data-permission-text=\"Issue title is private\" data-url=\"https://github.com/rails-girls-summer-of-code/rgsoc-teams/issues/853\">#853</a> where <a href=\"https://github.com/klappradla\" class=\"user-mention\">@klappradla</a> <a href=\"https://github.com/rails-girls-summer-of-code/rgsoc-teams/issues/853#issuecomment-329408374\">pointed out</a> that the 403s on S3 feed images might be related to the updated AWS gem.</p>", "body_text": "Follow-up to #853 where @klappradla pointed out that the 403s on S3 feed images might be related to the updated AWS gem.", "body": "Follow-up to #853 where @klappradla [pointed out](https://github.com/rails-girls-summer-of-code/rgsoc-teams/issues/853#issuecomment-329408374) that the 403s on S3 feed images might be related to the updated AWS gem."}