{"url": "https://api.github.com/repos/rails-girls-summer-of-code/rgsoc-teams/issues/comments/273481851", "html_url": "https://github.com/rails-girls-summer-of-code/rgsoc-teams/issues/583#issuecomment-273481851", "issue_url": "https://api.github.com/repos/rails-girls-summer-of-code/rgsoc-teams/issues/583", "id": 273481851, "user": {"login": "bitboxer", "id": 56195, "avatar_url": "https://avatars2.githubusercontent.com/u/56195?v=4", "gravatar_id": "", "url": "https://api.github.com/users/bitboxer", "html_url": "https://github.com/bitboxer", "followers_url": "https://api.github.com/users/bitboxer/followers", "following_url": "https://api.github.com/users/bitboxer/following{/other_user}", "gists_url": "https://api.github.com/users/bitboxer/gists{/gist_id}", "starred_url": "https://api.github.com/users/bitboxer/starred{/owner}{/repo}", "subscriptions_url": "https://api.github.com/users/bitboxer/subscriptions", "organizations_url": "https://api.github.com/users/bitboxer/orgs", "repos_url": "https://api.github.com/users/bitboxer/repos", "events_url": "https://api.github.com/users/bitboxer/events{/privacy}", "received_events_url": "https://api.github.com/users/bitboxer/received_events", "type": "User", "site_admin": false}, "created_at": "2017-01-18T13:59:43Z", "updated_at": "2017-01-18T13:59:43Z", "author_association": "MEMBER", "body_html": "<p>Let's discuss this in <a href=\"https://github.com/rails-girls-summer-of-code/rgsoc-teams/issues/588#issuecomment-273464790\">here</a>. No need to talk in 2 different positions about it ;)</p>", "body_text": "Let's discuss this in here. No need to talk in 2 different positions about it ;)", "body": "Let's discuss this in [here](https://github.com/rails-girls-summer-of-code/rgsoc-teams/issues/588#issuecomment-273464790). No need to talk in 2 different positions about it ;) "}