{"url": "https://api.github.com/repos/rails-girls-summer-of-code/rgsoc-teams/issues/comments/207841634", "html_url": "https://github.com/rails-girls-summer-of-code/rgsoc-teams/pull/450#issuecomment-207841634", "issue_url": "https://api.github.com/repos/rails-girls-summer-of-code/rgsoc-teams/issues/450", "id": 207841634, "user": {"login": "pratyusha972", "id": 13950129, "avatar_url": "https://avatars1.githubusercontent.com/u/13950129?v=4", "gravatar_id": "", "url": "https://api.github.com/users/pratyusha972", "html_url": "https://github.com/pratyusha972", "followers_url": "https://api.github.com/users/pratyusha972/followers", "following_url": "https://api.github.com/users/pratyusha972/following{/other_user}", "gists_url": "https://api.github.com/users/pratyusha972/gists{/gist_id}", "starred_url": "https://api.github.com/users/pratyusha972/starred{/owner}{/repo}", "subscriptions_url": "https://api.github.com/users/pratyusha972/subscriptions", "organizations_url": "https://api.github.com/users/pratyusha972/orgs", "repos_url": "https://api.github.com/users/pratyusha972/repos", "events_url": "https://api.github.com/users/pratyusha972/events{/privacy}", "received_events_url": "https://api.github.com/users/pratyusha972/received_events", "type": "User", "site_admin": false}, "created_at": "2016-04-09T19:38:46Z", "updated_at": "2016-04-09T19:38:46Z", "author_association": "CONTRIBUTOR", "body_html": "<p>Hello <a href=\"https://github.com/carpodaster\" class=\"user-mention\">@carpodaster</a> , Changes done. Thank you for reviewing! :)</p>", "body_text": "Hello @carpodaster , Changes done. Thank you for reviewing! :)", "body": "Hello @carpodaster , Changes done. Thank you for reviewing! :) \n"}