{"url": "https://api.github.com/repos/rails-girls-summer-of-code/rgsoc-teams/issues/comments/231016448", "html_url": "https://github.com/rails-girls-summer-of-code/rgsoc-teams/pull/465#issuecomment-231016448", "issue_url": "https://api.github.com/repos/rails-girls-summer-of-code/rgsoc-teams/issues/465", "id": 231016448, "user": {"login": "alicetragedy", "id": 3143348, "avatar_url": "https://avatars1.githubusercontent.com/u/3143348?v=4", "gravatar_id": "", "url": "https://api.github.com/users/alicetragedy", "html_url": "https://github.com/alicetragedy", "followers_url": "https://api.github.com/users/alicetragedy/followers", "following_url": "https://api.github.com/users/alicetragedy/following{/other_user}", "gists_url": "https://api.github.com/users/alicetragedy/gists{/gist_id}", "starred_url": "https://api.github.com/users/alicetragedy/starred{/owner}{/repo}", "subscriptions_url": "https://api.github.com/users/alicetragedy/subscriptions", "organizations_url": "https://api.github.com/users/alicetragedy/orgs", "repos_url": "https://api.github.com/users/alicetragedy/repos", "events_url": "https://api.github.com/users/alicetragedy/events{/privacy}", "received_events_url": "https://api.github.com/users/alicetragedy/received_events", "type": "User", "site_admin": false}, "created_at": "2016-07-07T08:33:50Z", "updated_at": "2016-07-07T08:33:50Z", "author_association": "OWNER", "body_html": "<p><a href=\"https://github.com/carpodaster\" class=\"user-mention\">@carpodaster</a> +1! when all is done, just post it in ongoing-tasks, I'm sure that some people will jump on the task :)</p>", "body_text": "@carpodaster +1! when all is done, just post it in ongoing-tasks, I'm sure that some people will jump on the task :)", "body": "@carpodaster +1! when all is done, just post it in ongoing-tasks, I'm sure that some people will jump on the task :)\n"}