{"url": "https://api.github.com/repos/mozilla-l10n/documentation/issues/comments/293275701", "html_url": "https://github.com/mozilla-l10n/documentation/pull/75#issuecomment-293275701", "issue_url": "https://api.github.com/repos/mozilla-l10n/documentation/issues/75", "id": 293275701, "user": {"login": "flodolo", "id": 3644868, "avatar_url": "https://avatars0.githubusercontent.com/u/3644868?v=4", "gravatar_id": "", "url": "https://api.github.com/users/flodolo", "html_url": "https://github.com/flodolo", "followers_url": "https://api.github.com/users/flodolo/followers", "following_url": "https://api.github.com/users/flodolo/following{/other_user}", "gists_url": "https://api.github.com/users/flodolo/gists{/gist_id}", "starred_url": "https://api.github.com/users/flodolo/starred{/owner}{/repo}", "subscriptions_url": "https://api.github.com/users/flodolo/subscriptions", "organizations_url": "https://api.github.com/users/flodolo/orgs", "repos_url": "https://api.github.com/users/flodolo/repos", "events_url": "https://api.github.com/users/flodolo/events{/privacy}", "received_events_url": "https://api.github.com/users/flodolo/received_events", "type": "User", "site_admin": false}, "created_at": "2017-04-11T14:11:30Z", "updated_at": "2017-04-11T14:11:30Z", "author_association": "COLLABORATOR", "body_html": "<p>Updated, thanks (will need a green tick to make GH happy)</p>", "body_text": "Updated, thanks (will need a green tick to make GH happy)", "body": "Updated, thanks (will need a green tick to make GH happy)"}