{"url": "https://api.github.com/repos/rails-girls-summer-of-code/rgsoc-teams/issues/comments/324160688", "html_url": "https://github.com/rails-girls-summer-of-code/rgsoc-teams/pull/816#issuecomment-324160688", "issue_url": "https://api.github.com/repos/rails-girls-summer-of-code/rgsoc-teams/issues/816", "id": 324160688, "user": {"login": "carpodaster", "id": 164400, "avatar_url": "https://avatars2.githubusercontent.com/u/164400?v=4", "gravatar_id": "", "url": "https://api.github.com/users/carpodaster", "html_url": "https://github.com/carpodaster", "followers_url": "https://api.github.com/users/carpodaster/followers", "following_url": "https://api.github.com/users/carpodaster/following{/other_user}", "gists_url": "https://api.github.com/users/carpodaster/gists{/gist_id}", "starred_url": "https://api.github.com/users/carpodaster/starred{/owner}{/repo}", "subscriptions_url": "https://api.github.com/users/carpodaster/subscriptions", "organizations_url": "https://api.github.com/users/carpodaster/orgs", "repos_url": "https://api.github.com/users/carpodaster/repos", "events_url": "https://api.github.com/users/carpodaster/events{/privacy}", "received_events_url": "https://api.github.com/users/carpodaster/received_events", "type": "User", "site_admin": false}, "created_at": "2017-08-22T21:44:57Z", "updated_at": "2017-08-22T21:44:57Z", "author_association": "OWNER", "body_html": "<p><a href=\"https://github.com/alicetragedy\" class=\"user-mention\">@alicetragedy</a> can you add Maud to the teams app on Heroku?</p>", "body_text": "@alicetragedy can you add Maud to the teams app on Heroku?", "body": "@alicetragedy can you add Maud to the teams app on Heroku?"}