{"url": "https://api.github.com/repos/rails-girls-summer-of-code/rgsoc-teams/issues/comments/78165349", "html_url": "https://github.com/rails-girls-summer-of-code/rgsoc-teams/pull/157#issuecomment-78165349", "issue_url": "https://api.github.com/repos/rails-girls-summer-of-code/rgsoc-teams/issues/157", "id": 78165349, "user": {"login": "carpodaster", "id": 164400, "avatar_url": "https://avatars2.githubusercontent.com/u/164400?v=4", "gravatar_id": "", "url": "https://api.github.com/users/carpodaster", "html_url": "https://github.com/carpodaster", "followers_url": "https://api.github.com/users/carpodaster/followers", "following_url": "https://api.github.com/users/carpodaster/following{/other_user}", "gists_url": "https://api.github.com/users/carpodaster/gists{/gist_id}", "starred_url": "https://api.github.com/users/carpodaster/starred{/owner}{/repo}", "subscriptions_url": "https://api.github.com/users/carpodaster/subscriptions", "organizations_url": "https://api.github.com/users/carpodaster/orgs", "repos_url": "https://api.github.com/users/carpodaster/repos", "events_url": "https://api.github.com/users/carpodaster/events{/privacy}", "received_events_url": "https://api.github.com/users/carpodaster/received_events", "type": "User", "site_admin": false}, "created_at": "2015-03-10T22:47:45Z", "updated_at": "2015-03-10T22:47:45Z", "author_association": "OWNER", "body_html": "<p><a href=\"https://github.com/sareg0\" class=\"user-mention\">@sareg0</a> no, I haven't done anything. Sure thing, do it in the morning \u2013 ping me if you have kwistions!</p>", "body_text": "@sareg0 no, I haven't done anything. Sure thing, do it in the morning \u2013 ping me if you have kwistions!", "body": "@sareg0 no, I haven't done anything. Sure thing, do it in the morning \u2013 ping me if you have kwistions!\n"}