{"url": "https://api.github.com/repos/rails-girls-summer-of-code/rgsoc-teams/pulls/comments/38958522", "pull_request_review_id": null, "id": 38958522, "diff_hunk": "@@ -2,169 +2,130 @@\n //\n // Site-wide used styles.\n \n-*\n-  box-sizing: border-box\n+// For debugging purposes\n+// *\n+//   border: 1px solid blue\n \n-body\n-  z-index: 0\n-  position: relative\n-  margin: 0 auto\n-  padding-bottom: 5em\n+html, body\n   color: $main\n   font-family: Lato, sans-serif\n   font-size: 15px\n-  a\n+  // For sticky footer\n+  height: 100%\n+\n+  a, a:hover\n     color: $railsred\n-  a:hover\n     color: $railsred\n-  &:before\n-    z-index: -1\n-    position: absolute\n-    left: 0\n-    right: 0\n-    top: 0\n-    height: 66px\n-    background-color: $railsred\n-    content: ' '\n-\n-body>header,\n-#content\n-  width: 1026px\n-  margin: 0 auto\n-\n-#footer\n-  footer\n-    border-top: 1px solid $lightgray\n-    position: relative\n-    top: 3em\n-    width: 1026px\n-    margin: 0 auto\n-\n-  ul\n-    padding-left: 0.5em\n-\n   li\n-    display: inline-block\n-    margin: 1em 0 0 0\n-\n-    &:last-child:after\n-      content: none\n-\n-    &:after\n-      content: '\uf005'\n-      display: inline-block\n-      width: 1em\n-      font-family: FontAwesome\n-      line-height: 1em\n-      color: $lightgray\n-\n-    a\n-      display: inline-block\n-      height: 48px\n-      text-decoration: none\n-\n-li\n-  list-style-type: none\n-\n-\n-header\n-  h1\n-    display: inline-block\n-    margin: 0\n-    width: 210px\n-    height: 58px\n-    a\n-      display: block\n-      height: 100%\n-      width: 100%\n-      background-image: asset-url('logo_subnavi.png')\n-      background-repeat: no-repeat\n-      background-size: cover\n-      background-position: -15px -1px\n-      text-indent: 999%\n-      white-space: nowrap\n+    list-style-type: none\n+  .text-right\n+    text-align: right\n+\n+// For sticky footer\n+#wrap\n+  min-height: 100%\n+  height: auto\n+  // Negative indent footer by its height\n+  margin: 0 auto -60px\n+  // Pad bottom by footer height\n+  padding: 0 0 60px\n+\n+#header\n+  height: 60px\n+  background-color: $railsred \n+  img\n+    width: 205px\n+    margin: -3px 0 0 -15px\n+\n+  a.button-burger\n+    @include icon($reorder)\n+    width: 35px\n+    height: 35px\n+    font-size: 24px\n+    text-decoration: none\n+    color: $railsred\n+    background: $white\n+    border-radius: 50%\n+    overflow: hidden\n+    margin-top: 12px\n+    @media screen and (min-width: 992px)\n+      display: none\n+    i\n+      position: relative\n+      top: 5px\n+      right: 7px\n+  ul\n+    padding: 0\n+    margin-top: -15px\n+    text-align: right\n+    li\n+      margin-bottom: 0.5rem\n \n-  nav\n-    clear: right\n-    float: right\n-    @include clearfix\n+  nav.user\n+    color: $darkgray\n \n-    &.top\n+  nav.top\n+    @media screen and (min-width: 992px)\n       ul\n-        text-align: center\n-        position: relative\n-        top: 5px\n-\n+        margin-top: -55px\n       li\n         display: inline-block\n-        margin: 1em 0 0 0\n-\n-        &:last-child:after\n-          content: none\n-\n         &:after\n-          content: ''\n-          display: inline-block\n-          height: 20px\n-          width: 40px\n-          background: asset-url('star.png') 16px 8px no-repeat\n-\n-        a\n-          display: inline-block\n-          height: 48px\n+          content: '\uf005'\n+          width: 2rem\n+          font-family: FontAwesome\n+          font-size: 0.7rem\n           color: $white\n-          text-decoration: none\n-\n-          &.active\n-            text-decoration: underline\n-            background-image: asset-url('header_nav_active.png')\n-            background-repeat: no-repeat\n-            background-position: center 32px\n-            text-decoration: none\n-\n-    &.user\n-      font-size: 0.9em\n-      color: $gray\n-\n-nav\n-  .back:before\n-    content: '\\2190'\n-    display: inline-block\n-    position: absolute\n-    margin-left: -1.5em\n-    margin-top: -1px\n+          margin: 0 0.6rem 0 0.6rem\n+        &:last-child:after, &:first-child:after\n+          content: none\n+      a\n+        color: white\n+        text-decoration: none\n \n-  &.page\n-    font-size: 0.9em\n+    // Changes bootstraps default collapsing breakpoint\n+    @media (min-width: 768px) and (max-width: 991px)", "path": "app/assets/stylesheets/global.css.sass", "position": null, "original_position": 205, "commit_id": "5cdbd5f36ee227622b61f8beacf7112030809ca8", "original_commit_id": "6a611f39ed705470705d4bb7c18254ab8f455489", "user": {"login": "marcgreenstock", "id": 287739, "avatar_url": "https://avatars2.githubusercontent.com/u/287739?v=4", "gravatar_id": "", "url": "https://api.github.com/users/marcgreenstock", "html_url": "https://github.com/marcgreenstock", "followers_url": "https://api.github.com/users/marcgreenstock/followers", "following_url": "https://api.github.com/users/marcgreenstock/following{/other_user}", "gists_url": "https://api.github.com/users/marcgreenstock/gists{/gist_id}", "starred_url": "https://api.github.com/users/marcgreenstock/starred{/owner}{/repo}", "subscriptions_url": "https://api.github.com/users/marcgreenstock/subscriptions", "organizations_url": "https://api.github.com/users/marcgreenstock/orgs", "repos_url": "https://api.github.com/users/marcgreenstock/repos", "events_url": "https://api.github.com/users/marcgreenstock/events{/privacy}", "received_events_url": "https://api.github.com/users/marcgreenstock/received_events", "type": "User", "site_admin": false}, "body": "same as my comment above you can use [$screen-sm](https://github.com/twbs/bootstrap-sass/blob/master/assets/stylesheets/bootstrap/_variables.scss#L300) and [$screen-sm-max](https://github.com/twbs/bootstrap-sass/blob/master/assets/stylesheets/bootstrap/_variables.scss#L321)\n", "created_at": "2015-09-08T17:59:57Z", "updated_at": "2015-09-09T08:03:03Z", "html_url": "https://github.com/rails-girls-summer-of-code/rgsoc-teams/pull/306#discussion_r38958522", "pull_request_url": "https://api.github.com/repos/rails-girls-summer-of-code/rgsoc-teams/pulls/306", "author_association": "MEMBER", "_links": {"self": {"href": "https://api.github.com/repos/rails-girls-summer-of-code/rgsoc-teams/pulls/comments/38958522"}, "html": {"href": "https://github.com/rails-girls-summer-of-code/rgsoc-teams/pull/306#discussion_r38958522"}, "pull_request": {"href": "https://api.github.com/repos/rails-girls-summer-of-code/rgsoc-teams/pulls/306"}}, "body_html": "<p>same as my comment above you can use <a href=\"https://github.com/twbs/bootstrap-sass/blob/master/assets/stylesheets/bootstrap/_variables.scss#L300\">$screen-sm</a> and <a href=\"https://github.com/twbs/bootstrap-sass/blob/master/assets/stylesheets/bootstrap/_variables.scss#L321\">$screen-sm-max</a></p>", "body_text": "same as my comment above you can use $screen-sm and $screen-sm-max"}