{"url": "https://api.github.com/repos/rails-girls-summer-of-code/rgsoc-teams/pulls/comments/112265219", "pull_request_review_id": 33565125, "id": 112265219, "diff_hunk": "@@ -0,0 +1 @@\n+$(\"#comments\").html(\"<%= j render 'comments', commentable: @comment.commentable, new_comment: @new_comment %>\")", "path": "app/views/comments/create.js.erb", "position": null, "original_position": 1, "commit_id": "0acb889c03d54146c7c525b10cdcab985df8aee8", "original_commit_id": "468100ab410be6086e8f0b527960a941e39387c9", "user": {"login": "klappradla", "id": 3491815, "avatar_url": "https://avatars3.githubusercontent.com/u/3491815?v=4", "gravatar_id": "", "url": "https://api.github.com/users/klappradla", "html_url": "https://github.com/klappradla", "followers_url": "https://api.github.com/users/klappradla/followers", "following_url": "https://api.github.com/users/klappradla/following{/other_user}", "gists_url": "https://api.github.com/users/klappradla/gists{/gist_id}", "starred_url": "https://api.github.com/users/klappradla/starred{/owner}{/repo}", "subscriptions_url": "https://api.github.com/users/klappradla/subscriptions", "organizations_url": "https://api.github.com/users/klappradla/orgs", "repos_url": "https://api.github.com/users/klappradla/repos", "events_url": "https://api.github.com/users/klappradla/events{/privacy}", "received_events_url": "https://api.github.com/users/klappradla/received_events", "type": "User", "site_admin": false}, "body": "Personal preference, but I prefer to use data attributes, e.g. `data-behavior=\"comment-container\" for things related to scripting in order to be able to fully leave IDs and classes to styling. ", "created_at": "2017-04-19T17:29:40Z", "updated_at": "2017-04-22T10:37:28Z", "html_url": "https://github.com/rails-girls-summer-of-code/rgsoc-teams/pull/742#discussion_r112265219", "pull_request_url": "https://api.github.com/repos/rails-girls-summer-of-code/rgsoc-teams/pulls/742", "author_association": "MEMBER", "_links": {"self": {"href": "https://api.github.com/repos/rails-girls-summer-of-code/rgsoc-teams/pulls/comments/112265219"}, "html": {"href": "https://github.com/rails-girls-summer-of-code/rgsoc-teams/pull/742#discussion_r112265219"}, "pull_request": {"href": "https://api.github.com/repos/rails-girls-summer-of-code/rgsoc-teams/pulls/742"}}, "body_html": "<p>Personal preference, but I prefer to use data attributes, e.g. `data-behavior=\"comment-container\" for things related to scripting in order to be able to fully leave IDs and classes to styling.</p>", "body_text": "Personal preference, but I prefer to use data attributes, e.g. `data-behavior=\"comment-container\" for things related to scripting in order to be able to fully leave IDs and classes to styling."}